k8swatcher/__init__.py
k8swatcher/__main__.py
k8swatcher/cli.py
k8swatcher/logging.py
k8swatcher-0.0.5.dist-info/LICENSE
k8swatcher-0.0.5.dist-info/METADATA
k8swatcher-0.0.5.dist-info/WHEEL
k8swatcher-0.0.5.dist-info/entry_points.txt
k8swatcher-0.0.5.dist-info/top_level.txt
k8swatcher-0.0.5.dist-info/RECORD
