Metadata-Version: 2.1
Name: k8swatcher
Version: 0.0.5
Summary: Library for watching kubernetes events
Home-page: https://github.com/bitsofinfo/k8swatcher
Author: bitsofinfo
Author-email: bitsofinfo.g@gmail.com
Classifier: Programming Language :: Python :: 3
Classifier: License :: OSI Approved :: MIT License
Classifier: Operating System :: OS Independent
Requires-Python: >=3.9
License-File: LICENSE
Requires-Dist: kubernetes (>=23.3.0)
Requires-Dist: typer (>=0.4.1)
Requires-Dist: pydantic (>=1.9.0)
